README.md
setup.py
mknn/__init__.py
mknn/mknn.py
mknn.egg-info/PKG-INFO
mknn.egg-info/SOURCES.txt
mknn.egg-info/dependency_links.txt
mknn.egg-info/requires.txt
mknn.egg-info/top_level.txt