Metadata-Version: 2.1
Name: mknn
Version: 0.0.1
Summary: Modified K-Nearest Neighbor
Home-page: https://github.com/nsandarma/Modified-K-Nearest-Neighbor
Author: nsandarma
Author-email: nsandarma@gmail.com
Classifier: Programming Language :: Python :: 3
Classifier: Operating System :: OS Independent
Requires-Python: >=3.10
